{
    "DESCRIPTION"      :   "########### PMI  ############",
   
    "config_template" :
    {
        "RUN-THIS-ON-MAC"  :   "http://mailtool.lan:8888/pmi2204/pmi-220426-10-mayo/pmi-220426-ID22.56-boost-mgm-DCE",
        "RUN-THIS-ON-PC"   :        "http://mailtool.lan/pmi2204/pmi-220426-10-mayo/pmi-220426-ID22.56-boost-mgm-DCE",
        "openHTML-MAC"     :   "file:///Users/armandoromero/Documents/devF1/mailtool.lan/html/pmi2204/pmi-220426-10-mayo/pmi-220426-ID22.56-boost-mgm-DCE.html",

        "Subject"          :   "Regala 30% de descuento a tus amigos para su primer Kit IQOS",
        "Preheader"        :   "Comparte la nueva forma de consumir tabaco y obtén hasta $1,500 MXN en beneficios",

        "PATH"             :   "Content Builder > Mexico > Commercial > MX_20220426_10 Mayo > 01_HTML",
        "Name-CustomerKey" :   
        [
            { 
                "name"        : "Boost MGM",
                "CustomerKey" : "NA"
            }
        ],
        "test-url"         :   
        [
            { "urlD" : "https://paginum.com/pmi2204/pmi-220426-10-mayo/pmi-220426-ID22.56-boost-mgm-DCE" } ,
            { "urlS" : "https://paginum.com/email/pmi2204/pmi-220426-10-mayo/pmi-220426-ID22.56-boost-mgm-DCE.html"  },
            { "urlS" : "http://mailtool.lan:8888/email/pmi2204/pmi-220426-10-mayo/pmi-220426-ID22.56-boost-mgm-DCE.html"},
            { "THIS" :  "urlD: Dynamic content / urlS: Static content" }

        ]
    },

    "SECTION_1"        :   "########### CONFIGURACION DE PLANTILLA ####################", 
    "BaseURLassets"    :   "",
    "BaseURLimg"       :   "",
    
    "HTMLstaticfile"   :   "pmi2204/pmi-220426-10-mayo/pmi-220426-ID22.56-boost-mgm-DCE.html",

    "trackmailopen"            :   "1",
    "trackmailaudience"        :   "1",    

    "target"                   :   "DCE",
    "footer_template"          :   "%%=ContentBlockbyKey(\"Commercial_MX_es_footer\")=%%",
    "footer_templateDCEGREY"   :   "%%=ContentBlockbyKey(\"Commercial_MX_es_footer\")=%%",
    "footer_templateDCEWHITE"  :   "%%=ContentBlockbyKey(\"Commercial_MX_es_footer_white\")=%%",

    "TwigTemplate"     :   "pmi/pmi-Brand-World-B01-600-v01.twig",
    "TwigFooterBlock"  :   "block-footer.twig",
    "Source"           :   "pmi-220426-ID22.56-boost-mgm-DCE",
    "isWebVer"         :   " ",
    
    "SECTION_2"        :   "############ CONTENIDOS #####################################",
    "PageTitle"        :   "",
    "PREHEADER"        :   "",
    "content_bgcolor"  :   "#FFFFFF",
    
      "blocks" : 
    [
        {
            "type": "img",
            "bgcolor": "transparent",
            "img": "https://image.e.iqos.com/lib/fe3a15707564067e7d1073/m/6/a46e7308-3690-450d-a795-11ee59dc0603.png",
            "imgHTML": "",
            "imgFSH": "",
            "imgDCE": "",
            "url": "#",
            "this": "IMG header IQOS Brand World"
        },
        {
            "type": "img",
            "bgcolor": "transparent",
            "img": "https://image.e.iqos.com/lib/fe3a15707564067e7d1073/m/6/561fe88a-a7d2-4235-ae0e-91b443c6e156.jpg",
            "imgHTML": "",
            "imgFSH": "",
            "imgDCE": "",
            "url": "#",
            "this": "IMG 22.56-1"
        },
        {
            "type": "img",
            "bgcolor": "transparent",
            "img": "https://image.e.iqos.com/lib/fe3a15707564067e7d1073/m/6/4c7e2c12-7929-42fa-93ca-a2c7cb40921c.png",
            "imgHTML": "",
            "imgFSH": "",
            "imgDCE": "",
            "url": "#",
            "this": "IMG 22.56-2"
        },
        {
            "type": "greeting_v2",
            "fontweight": "700",
            "color_greeting": "#333333",
            "color_bkg": "transparent",
            "margin_top": "70",
            "margin_bottom": "50",
            "greeting": "Hola, %%=ProperCase(first_name)=%%",
            "greetingBW": "<span style=\"color:#e4ab68;\">Hola,</span> %%first_name%%",
            "greetingFSH": "Hola, %%FirstName%%",
            "greetingHTML": "Hola, %%=ProperCase(first_name)=%%",
            "greetingDCE": "Hola, %%=ProperCase(first_name)=%%",
            "this": "Hola [nombre]"
        },
        {
            "type": "p",
            "font": "Cabin",
            "fontweight": "300",
            "fontsize": "18",
            "height": "26",
            "width": "70%",
            "align": "center",
            "color": "#333333",
            "color_bkg": "transparent",
            "margin_top": "0",
            "margin_bottom": "50",
            "content": "Entre amigos<span style=\"font-size:12px;\"><sup>(1)</sup></span> no hay secretos, hay códigos.<br><br>Este mes comparte tu Código Único y regala <span style=\"color:#00d1d2;font-size:22px;font-weight:700;\">30% de descuento</span> a tus amigos en la compra de su primer Kit IQOS en lugar del <b>20% habitual.</b>",
            "this": "TXT"
        },
        {
            "type": "img",
            "bgcolor": "transparent",
            "img": "https://image.e.iqos.com/lib/fe3a15707564067e7d1073/m/6/1f1c2d35-e93f-4975-abdc-e579d278697e.jpg",
            "imgHTML": "",
            "imgFSH": "",
            "imgDCE": "",
            "url": "#",
            "this": "IMG 22.56-3"
        },
        {
            "type": "columns",
            "font": "Cabin",
            "margin_sides": "0",
            "margin_top": "0",
            "margin_bottom": "0",
            "color_bkg": "#faf7f4",
            "this": "",
            "columns": [
                {
                    "coltype": "multirows",
                    "color_bkg": "#faf7f4",
                    "widthp100": "100",
                    "rows": [
                        {
                            "rowtype": "img",
                            "img": "https://image.e.iqos.com/lib/fe3a15707564067e7d1073/m/6/2fbea76e-b3b8-4cdc-be70-88217e60baa4.png",
                            "color_bkg": "#faf7f4",
                            "margin_top": "30",
                            "margin_bottom": "0",
                            "imgWidth": "100",
                            "align": "center",
                            "imgulr": "#",
                            "THISIMG": "22.55-ico1"
                        },
                        {
                            "rowtype": "p",
                            "p": "Comparte tu codigo único y regala",
                            "color_bkg": "#faf7f4",
                            "p_fontweight": "300",
                            "p_fontsize": "18px",
                            "p_height": "26px",
                            "p_align": "center",
                            "p_color": "#333333",
                            "margin_top": "20",
                            "margin_bottom": "0"
                        },
                        {
                            "rowtype": "p",
                            "p": "30% de descuento<span style=\"font-size:16px;\"><sup>(3)</sup></span>",
                            "color_bkg": "#faf7f4",
                            "p_fontweight": "700",
                            "p_fontsize": "24px",
                            "p_height": "28px",
                            "p_align": "center",
                            "p_color": "#00d1d2",
                            "margin_top": "0",
                            "margin_bottom": "0"
                        },
                        {
                            "rowtype": "p",
                            "p": "a tus amigos en la compra de su primer<br> Kit IQOS en lugar del <b>20% habitual.</b>",
                            "color_bkg": "#faf7f4",
                            "p_fontweight": "300",
                            "p_fontsize": "18px",
                            "p_height": "26px",
                            "p_align": "center",
                            "p_color": "#333333",
                            "margin_top": "0",
                            "margin_bottom": "0"
                        },
                        {
                            "rowtype": "pframed",
                            "color_bkg": "#faf7f4",
                            "p": "%%=v(@voucher_code)=%%",
                            "fontweight": "700",
                            "fontsize": "22",
                            "lineheight": "22",
                            "align": "center",
                            "width": "40%",
                            "margin_top": "20",
                            "margin_bottom": "0",
                            "color": "#FFFFFF",
                            "framecolor": "#34313d",
                            "framebgcolor": "#34313d",
                            "framepadding": "10",
                            "border": "1",
                            "this": ""
                        },
                        {
                            "rowtype": "img",
                            "img": "https://image.e.iqos.com/lib/fe3a15707564067e7d1073/m/6/ee899f79-7395-452e-9990-2d94826cd7c5.png",
                            "color_bkg": "#faf7f4",
                            "margin_top": "20",
                            "margin_bottom": "0",
                            "imgWidth": "260",
                            "align": "center",
                            "donde_codificar_la_siguiente url": "https://www.urlencoder.org/",
                            "url_ctaDECODED": "whatsapp://send?text=",
                            "text2encode": "Te regalo 30% de descuento en la compra de tu primer Kit IQOS. No olvides utilizar mi código %%=v(@voucher_code)=%% al comprar.",
                            "url_cta1": "whatsapp://send?text=",
                            "url_cta2": "https://wa.me/?text=",
                            "url_cta3": "https://web.whatsapp.com/send?text=",
                            "imgulr": "https://wa.me/?text=Te%20regalo%2030%25%20de%20descuento%20en%20la%20compra%20de%20tu%20primer%20Kit%20IQOS.%20No%20olvides%20utilizar%20mi%20c%C3%B3digo%20%25%25%3Dv%28%40voucher_code%29%3D%25%25%20al%20comprar.",
                            "THISIMG": "cta-bw-comparte-tu-codigo-unico"
                        },
                        {
                            "rowtype": "img",
                            "img": "https://image.e.iqos.com/lib/fe3a15707564067e7d1073/m/6/cac508bd-32bf-46d2-ad44-4efa326e0c11.png",
                            "color_bkg": "#faf7f4",
                            "margin_top": "40",
                            "margin_bottom": "0",
                            "imgWidth": "100",
                            "align": "center",
                            "imgulr": "#",
                            "THISIMG": "22.55-ico2"
                        },
                        {
                            "rowtype": "p",
                            "p": "Por cada amigo que utilice tu código y <br>registre su Kit IQOS en iqos.com, tu recibirás",
                            "color_bkg": "#faf7f4",
                            "p_fontweight": "300",
                            "p_fontsize": "18px",
                            "p_height": "26px",
                            "p_align": "center",
                            "p_color": "#333333",
                            "margin_top": "20",
                            "margin_bottom": "0"
                        },
                        {
                            "rowtype": "p",
                            "p": "$300 MXN en beneficios<span style=\"font-size:16px;\"><sup>(2)</sup></span>.",
                            "color_bkg": "#faf7f4",
                            "p_fontweight": "700",
                            "p_fontsize": "24px",
                            "p_height": "30px",
                            "p_align": "center",
                            "p_color": "#00d1d2",
                            "margin_top": "0",
                            "margin_bottom": "40"
                        }
                    ]
                }
            ]
        },
        {
            "type": "p",
            "font": "Cabin",
            "fontweight": "700",
            "fontsize": "28",
            "height": "32",
            "width": "70%",
            "align": "center",
            "color": "#333333",
            "color_bkg": "transparent",
            "margin_top": "50",
            "margin_bottom": "0",
            "content": "Comparte, regala y recibe.",
            "this": "TXT"
        },
        {
            "type": "p",
            "font": "Cabin",
            "fontweight": "700",
            "fontsize": "26",
            "height": "30",
            "width": "70%",
            "align": "center",
            "color": "#00d1d2",
            "color_bkg": "transparent",
            "margin_top": "20",
            "margin_bottom": "50",
            "content": "#IQODIGOS",
            "this": "#IQODIGOS"
        },
        {
            "type": "disclaimer",
            "bgcolor": "transparent",
            "align": "justify",
            "color": "#333333",
            "fontsize": "11",
            "txt": "(1) Solo para fumadores adultos.<br>(2) Recompensa no canjeable por dinero en efectivo y redimible en Tiendas IQOS, IQOS Corners en Sanborns seleccionados y iqos.com. No canjeable por productos de tabaco. Limitado a los primeros 5 amigos referidos que compren y registren su primer dispositivo con tu código único. Redimible solo una vez por usuario registrado (con cuenta creada en www.iqos.com). Cada recompensa deberá ser canjeada en su totalidad en una sola exhibición. Consulta Términos y Condiciones del Programa. Descuento del 30% válido del 1 al 31 de mayo 2022.<br>(3) Consulta Términos y Condiciones. Válido en la compra y registro del primer dispositivo (IQOS Holder + Cargador IQOS) de cada amigo referido. Para obtener su descuento, el amigo referido debe registrarse y registrar su dispositivo en iqos.com, y hacerlo válido en Tiendas IQOS, IQOS Corners en Sanborns seleccionados y iqos.com. Descuento no válido en productos de tabaco.",
            "this": "LEGALES"
        },
        {
            "type": "pframed",
            "fontweight": "300",
            "fontsize": "11",
            "height": "11",
            "width": "80%",
            "align": "justify",
            "color": "#333333",
            "color_bkg": "transparent",
            "color_boxbkg": "#FFFFFF",
            "margin_top": "15",
            "margin_bottom": "15",
            "framecolor": "#000000",
            "framepadding": "15",
            "content": "<b>Información importante:</b> IQOS es un dispositivo electrónico que, al calentar unidades de tabaco, entrega nicotina, la cual es adictiva y no está libre de riesgo. Prohibida su venta a menores de edad.",
            "this": "Información importante"
        },
        {
            "type": "disclaimer",
            "bgcolor": "transparent",
            "align": "justify",
            "color": "#333333",
            "fontsize": "11",
            "txt": "Consulta nuestro aviso de privacidad con base en el cual son tratados tus datos personales <a href=\"https://www.pmiprivacy.com/es-la/consumer\" alias=\"footer_pmi_privacy\" style=\"text-decoration:underline;\" target=\"_blank\">aquí</a>.",
            "this": "PRIVACY NOTICE"
        },
        {
            "type": "spacer",
            "height": "25",
            "color_bkg": "transparent",
            "this": "spacer"
        },
        {
            "type": "footer_bw_v1_lowercase"
        }
    ],

    "END"            :   "#######################"

    }
    